mopidy_slack/__init__.py
mopidy_slack/connector.py
mopidy_slack/ext.conf
mopidy_slack/song_notification.py
mopidy_slack/utils.py
mopidy_slack/command/__init__.py
mopidy_slack/command/help.py
mopidy_slack/command/keep.py
mopidy_slack/command/listener.py
mopidy_slack/command/next.py
mopidy_slack/command/request.py
mopidy_slack/command/start.py
Mopidy_Slack-0.1.0.dist-info/LICENSE
Mopidy_Slack-0.1.0.dist-info/METADATA
Mopidy_Slack-0.1.0.dist-info/WHEEL
Mopidy_Slack-0.1.0.dist-info/entry_points.txt
Mopidy_Slack-0.1.0.dist-info/top_level.txt
Mopidy_Slack-0.1.0.dist-info/RECORD
