Metadata-Version: 2.1
Name: Mopidy-Slack
Version: 0.1.0
Summary: Control your mopidy instance from slack
Home-page: https://github.com/ablanchard/mopidy-slack
Author: Alexandre Blanchard
License: Apache License, Version 2.0
Platform: UNKNOWN
Classifier: Environment :: No Input/Output (Daemon)
Classifier: Intended Audience :: End Users/Desktop
Classifier: License :: OSI Approved :: Apache Software License
Classifier: Operating System :: OS Independent
Classifier: Programming Language :: Python :: 3
Classifier: Topic :: Multimedia :: Sound/Audio :: Players
Requires-Dist: setuptools
Requires-Dist: Mopidy (>=3.0.0)
Requires-Dist: Pykka (>=1.1)
Requires-Dist: slackclient (>=2.0.0)
